ubpe_cython/__init__.py
ubpe_cython/libubpe.so
ubpe_cython-0.2.4.dist-info/METADATA
ubpe_cython-0.2.4.dist-info/WHEEL
ubpe_cython-0.2.4.dist-info/licenses/LICENSE
ubpe_cython-0.2.4.dist-info/RECORD
