Metadata-Version: 2.4
Name: ubpe-cython
Version: 0.2.4
Summary: Cython implementation of UBPE tokenization algorithm (C++ backend).
License-File: LICENSE
Author: Scurrra (Ilja Baroŭski)
Author-email: iscurrra@gmail.com
Requires-Python: >=3.12
Classifier: Programming Language :: Python :: 3
Classifier: Development Status :: 4 - Beta
Classifier: Programming Language :: Cython
Classifier: Programming Language :: C++
Project-URL: Issues, https://github.com/Scurrra/ubpe-cython/issues
Project-URL: Repository, https://github.com/Scurrra/ubpe-cython.git
